MANIFEST.in
README.txt
setup.py
doc/Makefile
doc/make.bat
doc/build/doctrees/cpc.doctree
doc/build/doctrees/environment.pickle
doc/build/doctrees/index.doctree
doc/build/doctrees/mvmds.doctree
doc/build/doctrees/mvsc.doctree
doc/build/doctrees/mvtsne.doctree
doc/build/doctrees/plot_mvmds.doctree
doc/build/doctrees/plot_mvsc.doctree
doc/build/doctrees/plot_mvtsne.doctree
doc/build/html/.buildinfo
doc/build/html/cpc.html
doc/build/html/genindex.html
doc/build/html/index.html
doc/build/html/mvmds.html
doc/build/html/mvsc.html
doc/build/html/mvtsne.html
doc/build/html/objects.inv
doc/build/html/plot_mvmds.html
doc/build/html/plot_mvsc.html
doc/build/html/plot_mvtsne.html
doc/build/html/py-modindex.html
doc/build/html/search.html
doc/build/html/searchindex.js
doc/build/html/_images/mvmds.png
doc/build/html/_images/mvtsne-6.png
doc/build/html/_sources/cpc.rst.txt
doc/build/html/_sources/index.rst.txt
doc/build/html/_sources/mvmds.rst.txt
doc/build/html/_sources/mvsc.rst.txt
doc/build/html/_sources/mvtsne.rst.txt
doc/build/html/_sources/plot_mvmds.rst.txt
doc/build/html/_sources/plot_mvsc.rst.txt
doc/build/html/_sources/plot_mvtsne.rst.txt
doc/build/html/_static/ajax-loader.gif
doc/build/html/_static/alabaster.css
doc/build/html/_static/basic.css
doc/build/html/_static/classic.css
doc/build/html/_static/comment-bright.png
doc/build/html/_static/comment-close.png
doc/build/html/_static/comment.png
doc/build/html/_static/contents.png
doc/build/html/_static/custom.css
doc/build/html/_static/doctools.js
doc/build/html/_static/down-pressed.png
doc/build/html/_static/down.png
doc/build/html/_static/file.png
doc/build/html/_static/jquery-3.1.0.js
doc/build/html/_static/jquery.js
doc/build/html/_static/minus.png
doc/build/html/_static/mvmds.png
doc/build/html/_static/mvtsne-6.png
doc/build/html/_static/nature.css
doc/build/html/_static/navigation.png
doc/build/html/_static/plus.png
doc/build/html/_static/pygments.css
doc/build/html/_static/searchtools.js
multiview.egg-info/PKG-INFO
multiview.egg-info/SOURCES.txt
multiview.egg-info/dependency_links.txt
multiview.egg-info/not-zip-safe
multiview.egg-info/top_level.txt
