Metadata-Version: 1.1
Name: multiview
Version: 1.0
Summary: Multiview clustering and dimensionality reduction
Home-page: https://github.com/mariceli3/multiview
Author: María Araceli Burgueño Caballero
Author-email: mburgueno@uoc.edu
License: UNKNOWN
Keywords: multiview,clustering,dimensionality reduction
Platform: UNKNOWN
Classifier: Programming Language :: Python
Classifier: Programming Language :: Python :: 2
Classifier: Programming Language :: Python :: 2.7
Classifier: Programming Language :: Python :: 3
Classifier: Programming Language :: Python :: 3.4
Classifier: Programming Language :: Python :: 3.5
Classifier: Programming Language :: Python :: 3.6
Classifier: Development Status :: 3 - Alpha
Classifier: Environment :: Other Environment
Classifier: Intended Audience :: Developers
Classifier: Intended Audience :: Science/Research
Classifier: License :: OSI Approved :: BSD License
Classifier: Operating System :: OS Independent
Classifier: Topic :: Software Development :: Libraries :: Python Modules
Classifier: Topic :: Scientific/Engineering :: Artificial Intelligence
